mcp_server_excel/__init__.py
mcp_server_excel/server.py
baiyx_mcp_server_excel-0.1.6.dist-info/METADATA
baiyx_mcp_server_excel-0.1.6.dist-info/WHEEL
baiyx_mcp_server_excel-0.1.6.dist-info/entry_points.txt
baiyx_mcp_server_excel-0.1.6.dist-info/RECORD
