Metadata-Version: 2.4
Name: baiyx-mcp-server-excel
Version: 0.1.6
Summary: A Model Context Protocol server providing Excel reading and writing functionality
Author-email: baiyx <baiyx@example.com>
License: MIT
Keywords: excel,llm,mcp
Classifier: Development Status :: 4 - Beta
Classifier: Intended Audience :: Developers
Classifier: License :: OSI Approved :: MIT License
Classifier: Programming Language :: Python :: 3
Classifier: Programming Language :: Python :: 3.10
Requires-Python: >=3.10
Requires-Dist: mcp>=1.6.0
Requires-Dist: openpyxl>=3.1.2
Requires-Dist: pandas>=2.0.0
Requires-Dist: pydantic>=2.0.0
